ding/__init__.py
ding/lookup.py
ding/otp.py
ding/sdk.py
ding/sdkconfiguration.py
ding/models/__init__.py
ding/models/components/__init__.py
ding/models/components/createauthenticationrequest.py
ding/models/components/createauthenticationresponse.py
ding/models/components/createcheckrequest.py
ding/models/components/createcheckresponse.py
ding/models/components/lookupresponse.py
ding/models/components/retryauthenticationrequest.py
ding/models/components/retryauthenticationresponse.py
ding/models/components/security.py
ding/models/errors/__init__.py
ding/models/errors/errorresponse.py
ding/models/errors/sdkerror.py
ding/models/operations/__init__.py
ding/models/operations/check.py
ding/models/operations/create_autentication.py
ding/models/operations/lookup.py
ding/models/operations/retry.py
ding/utils/__init__.py
ding/utils/retries.py
ding/utils/utils.py
ding_client_sdk-1.3.0.dist-info/LICENSE.md
ding_client_sdk-1.3.0.dist-info/METADATA
ding_client_sdk-1.3.0.dist-info/WHEEL
ding_client_sdk-1.3.0.dist-info/top_level.txt
ding_client_sdk-1.3.0.dist-info/RECORD
